LICENSE
README.md
pyproject.toml
setup.py
src/vecs/__init__.py
src/vecs/client.py
src/vecs/collection.py
src/vecs/exc.py
src/vecs.egg-info/PKG-INFO
src/vecs.egg-info/SOURCES.txt
src/vecs.egg-info/dependency_links.txt
src/vecs.egg-info/requires.txt
src/vecs.egg-info/top_level.txt
src/vecs/adapter/__init__.py
src/vecs/adapter/base.py
src/vecs/adapter/markdown.py
src/vecs/adapter/noop.py
src/vecs/adapter/text.py