Metadata-Version: 2.1
Name: vecs
Version: 0.4.1
Summary: pgvector client
Home-page: https://github.com/supabase/vecs
Author: Oliver Rice
License: MIT
Platform: UNKNOWN
Classifier: Development Status :: 4 - Beta
Classifier: Natural Language :: English
Classifier: Operating System :: OS Independent
Classifier: Programming Language :: Python
Classifier: Programming Language :: Python :: 3
Classifier: Programming Language :: Python :: 3.8
Classifier: Programming Language :: Python :: 3.9
Classifier: Programming Language :: Python :: 3.10
Classifier: Programming Language :: Python :: 3.11
Classifier: Programming Language :: Python :: 3.12
Provides-Extra: dev
Provides-Extra: docs
Provides-Extra: text_embedding
License-File: LICENSE
